chronicals/__init__.py
chronicals/py.typed
chronicals/config/__init__.py
chronicals/config/config.py
chronicals/config/sota_config.py
chronicals/data/__init__.py
chronicals/data/data_loader.py
chronicals/data/sequence_packer.py
chronicals/data/sequence_packer_v2.py
chronicals/kernels/__init__.py
chronicals/kernels/cut_cross_entropy.py
chronicals/kernels/flash_attention_optimizer.py
chronicals/kernels/fused_lora_kernels.py
chronicals/kernels/fused_qk_rope.py
chronicals/kernels/fused_rope.py
chronicals/kernels/triton_kernels.py
chronicals/lora/__init__.py
chronicals/lora/dora_adapter.py
chronicals/lora/gradient_checkpointing_lora.py
chronicals/lora/lora_optimized.py
chronicals/lora/lora_presets.py
chronicals/optimizers/__init__.py
chronicals/optimizers/fused_adamw.py
chronicals/optimizers/lora_plus_optimizer.py
chronicals/optimizers/optimizers.py
chronicals/optimizers/optimizers_8bit.py
chronicals/training/__init__.py
chronicals/training/async_activation_offload.py
chronicals/training/chronicals_trainer.py
chronicals/training/cuda_graph_manager.py
chronicals/training/gradient_checkpointing.py
chronicals/utils/__init__.py
chronicals/utils/compile_utils.py
chronicals/utils/fp8_deepseek.py
chronicals/utils/fp8_utils.py
chronicals/utils/profiling_utils.py
chronicals/utils/visual_reporter.py
chronicals-0.1.4.dist-info/licenses/LICENSE
chronicals-0.1.4.dist-info/licenses/NOTICE
chronicals-0.1.4.dist-info/METADATA
chronicals-0.1.4.dist-info/WHEEL
chronicals-0.1.4.dist-info/entry_points.txt
chronicals-0.1.4.dist-info/top_level.txt
chronicals-0.1.4.dist-info/RECORD
