Metadata-Version: 2.4
Name: chronicals
Version: 0.1.4
Summary: High-Performance LLM Fine-Tuning Framework - 3.51x faster than Unsloth
Home-page: https://github.com/Ajwebdevs/Chronicals
Author: Arjun S. Nair
Author-email: "Arjun S. Nair" <5minutepodcastforyou@gmail.com>
Maintainer-email: "Arjun S. Nair" <5minutepodcastforyou@gmail.com>
License: Apache-2.0
Project-URL: Homepage, https://github.com/Ajwebdevs/Chronicals
Project-URL: Documentation, https://github.com/Ajwebdevs/Chronicals#readme
Project-URL: Repository, https://github.com/Ajwebdevs/Chronicals.git
Project-URL: Issues, https://github.com/Ajwebdevs/Chronicals/issues
Project-URL: Changelog, https://github.com/Ajwebdevs/Chronicals/releases
Keywords: llm,fine-tuning,deep-learning,transformers,triton,lora,flash-attention,pytorch,gpu,optimization,machine-learning,nlp
Classifier: Development Status :: 4 - Beta
Classifier: Intended Audience :: Developers
Classifier: Intended Audience :: Science/Research
Classifier: License :: OSI Approved :: Apache Software License
Classifier: Operating System :: OS Independent
Classifier: Programming Language :: Python :: 3
Classifier: Programming Language :: Python :: 3.8
Classifier: Programming Language :: Python :: 3.9
Classifier: Programming Language :: Python :: 3.10
Classifier: Programming Language :: Python :: 3.11
Classifier: Programming Language :: Python :: 3.12
Classifier: Topic :: Scientific/Engineering :: Artificial Intelligence
Classifier: Topic :: Software Development :: Libraries :: Python Modules
Requires-Python: >=3.8
License-File: LICENSE
License-File: NOTICE
Requires-Dist: torch>=2.1.0
Requires-Dist: transformers>=4.36.0
Requires-Dist: datasets>=2.14.0
Requires-Dist: accelerate>=0.25.0
Requires-Dist: peft>=0.7.0
Requires-Dist: tqdm>=4.65.0
Requires-Dist: numpy>=1.24.0
Requires-Dist: safetensors>=0.4.0
Provides-Extra: triton
Requires-Dist: triton>=2.1.0; extra == "triton"
Provides-Extra: flash-attn
Requires-Dist: flash-attn>=2.4.0; extra == "flash-attn"
Requires-Dist: ninja; extra == "flash-attn"
Provides-Extra: kernels
Requires-Dist: triton>=2.1.0; extra == "kernels"
Requires-Dist: liger-kernel; extra == "kernels"
Requires-Dist: cut-cross-entropy; extra == "kernels"
Requires-Dist: xformers; extra == "kernels"
Requires-Dist: einops; extra == "kernels"
Provides-Extra: 8bit
Requires-Dist: bitsandbytes>=0.41.0; extra == "8bit"
Provides-Extra: training
Requires-Dist: trl; extra == "training"
Requires-Dist: huggingface_hub>=0.19.0; extra == "training"
Requires-Dist: sentencepiece; extra == "training"
Requires-Dist: protobuf; extra == "training"
Requires-Dist: tiktoken; extra == "training"
Provides-Extra: logging
Requires-Dist: wandb>=0.16.0; extra == "logging"
Requires-Dist: tensorboard>=2.15.0; extra == "logging"
Requires-Dist: matplotlib>=3.7.0; extra == "logging"
Requires-Dist: pandas; extra == "logging"
Provides-Extra: profiling
Requires-Dist: py-spy; extra == "profiling"
Provides-Extra: all
Requires-Dist: triton>=2.1.0; extra == "all"
Requires-Dist: flash-attn>=2.4.0; extra == "all"
Requires-Dist: ninja; extra == "all"
Requires-Dist: liger-kernel; extra == "all"
Requires-Dist: cut-cross-entropy; extra == "all"
Requires-Dist: xformers; extra == "all"
Requires-Dist: einops; extra == "all"
Requires-Dist: bitsandbytes>=0.41.0; extra == "all"
Requires-Dist: trl; extra == "all"
Requires-Dist: huggingface_hub>=0.19.0; extra == "all"
Requires-Dist: sentencepiece; extra == "all"
Requires-Dist: protobuf; extra == "all"
Requires-Dist: tiktoken; extra == "all"
Requires-Dist: wandb>=0.16.0; extra == "all"
Requires-Dist: tensorboard>=2.15.0; extra == "all"
Requires-Dist: matplotlib>=3.7.0; extra == "all"
Requires-Dist: pandas; extra == "all"
Provides-Extra: dev
Requires-Dist: pytest>=7.4.0; extra == "dev"
Requires-Dist: pytest-cov>=4.1.0; extra == "dev"
Requires-Dist: black>=23.0.0; extra == "dev"
Requires-Dist: isort>=5.12.0; extra == "dev"
Requires-Dist: flake8>=6.1.0; extra == "dev"
Requires-Dist: mypy>=1.7.0; extra == "dev"
Requires-Dist: pre-commit>=3.6.0; extra == "dev"
Dynamic: author
Dynamic: home-page
Dynamic: license-file
Dynamic: requires-python
